finchnmr/__init__.py
finchnmr/analysis.py
finchnmr/library.py
finchnmr/model.py
finchnmr/substance.py
finchnmr/xml_parser.py
finchnmr-0.0.0b1.dist-info/LICENSE.md
finchnmr-0.0.0b1.dist-info/METADATA
finchnmr-0.0.0b1.dist-info/WHEEL
finchnmr-0.0.0b1.dist-info/top_level.txt
finchnmr-0.0.0b1.dist-info/RECORD
