Metadata-Version: 2.1
Name: finchnmr
Version: 0.0.0b1
Summary: [FI]tti[N]g 13[C] 1[H] HSQC [NMR]
Author-email: "Nathan A. Mahynski" <nathan.mahynski@gmail.com>, "David A. Sheen" <david.sheen@nist.gov>
Maintainer-email: "Nathan A. Mahynski" <nathan.mahynski@gmail.com>, "David A. Sheen" <david.sheen@nist.gov>
License: # NIST Software Licensing Statement
Project-URL: Repository, https://github.com/mahynski/finchnmr.git
Project-URL: Documentation, https://finchnmr.readthedocs.io/
Project-URL: Issues, https://github.com/mahynski/finchnmr/issues
Classifier: Development Status :: 4 - Beta
Classifier: Intended Audience :: Science/Research
Classifier: Operating System :: OS Independent
Classifier: Programming Language :: Python :: 3
Requires-Python: >=3.10
License-File: LICENSE.md
Requires-Dist: xml-python==0.4.3
Requires-Dist: nmrglue==0.11
Requires-Dist: tqdm>=4.66.1
Requires-Dist: numpy<2.0.0,>=1.23
Requires-Dist: scikit-image==0.24.0
Requires-Dist: scipy>=1.14.1
Requires-Dist: scikit-learn
Requires-Dist: matplotlib>=3.7.2
Requires-Dist: pandas==2.2
Requires-Dist: pre-commit==3.3.3
Requires-Dist: pytest>=7.4.0
Requires-Dist: ipython<=8.21
Requires-Dist: ipykernel
Requires-Dist: nbformat>=4.2.0
Requires-Dist: plotly>=5.24.1
Requires-Dist: mypy
Requires-Dist: sphinx
Provides-Extra: all
